CHANGES.rst
MANIFEST.in
README.rst
setup.py
tomcom/__init__.py
tomcom.plone.base.egg-info/PKG-INFO
tomcom.plone.base.egg-info/SOURCES.txt
tomcom.plone.base.egg-info/dependency_links.txt
tomcom.plone.base.egg-info/entry_points.txt
tomcom.plone.base.egg-info/namespace_packages.txt
tomcom.plone.base.egg-info/not-zip-safe
tomcom.plone.base.egg-info/requires.txt
tomcom.plone.base.egg-info/top_level.txt
tomcom/plone/__init__.py
tomcom/plone/base/__init__.py
tomcom/plone/base/configure.zcml
tomcom/plone/base/overrides.zcml
tomcom/plone/base/permissions.zcml
tomcom/plone/base/profiles.zcml
tomcom/plone/base/ptfpatch.zcml
tomcom/plone/base/locales/.gitignore
tomcom/plone/base/locales/de/LC_MESSAGES/plone.po
tomcom/plone/base/overrides/templates/batchnavigation_bootstrap.pt
tomcom/plone/base/overrides/templates/folder_contents.pt
tomcom/plone/base/overrides/templates/folder_contents_table.pt
tomcom/plone/base/overrides/templates/manage-viewletmanager.pt
tomcom/plone/base/overrides/templates/manage-viewlets.pt
tomcom/plone/base/overrides/templates/memberregistration.pt
tomcom/plone/base/overrides/templates/refbrowser_popup.pt
tomcom/plone/base/overrides/templates/reload.pt
tomcom/plone/base/overrides/templates/usergroups_groupsoverview.pt
tomcom/plone/base/overrides/templates/usergroups_usersoverview.pt
tomcom/plone/base/patches/__init__.py
tomcom/plone/base/patches/image.py
tomcom/plone/base/profiles/default/actions.xml
tomcom/plone/base/profiles/default/cssregistry.xml
tomcom/plone/base/profiles/default/jsregistry.xml
tomcom/plone/base/profiles/default/metadata.xml
tomcom/plone/base/profiles/default/rolemap.xml
tomcom/plone/base/profiles/default/skins.xml
tomcom/plone/base/resource/css/custom_bootstrap.css
tomcom/plone/base/resource/css/normalize.css
tomcom/plone/base/resource/css/statusmessage.css
tomcom/plone/base/resource/css/toolbar.css
tomcom/plone/base/resource/img/glyphicons-halflings-white.png
tomcom/plone/base/resource/img/glyphicons-halflings.png
tomcom/plone/base/resource/js/confirm.js
tomcom/plone/base/resource/js/helper.js
tomcom/plone/base/resource/js/statusmessage.js
tomcom/plone/base/resource/js/toolbar.js
tomcom/plone/base/skins/tpb_plone_css/IEFixes.css
tomcom/plone/base/skins/tpb_plone_css/RTL.css
tomcom/plone/base/skins/tpb_plone_css/authoring.css
