Metadata-Version: 1.1
Name: tomcom.plone.base
Version: 4.3.1.4
Summary: Little helpers
Home-page: https://github.com/tomcom-de/tomcom.plone.base
Author: tomcom GmbH
Author-email: mailto:info@tomcom.de
License: GPL2
Keywords: tomcom plone
Platform: UNKNOWN
Classifier: Framework :: Plone
Classifier: Programming Language :: Python
Classifier: Topic :: Software Development :: Libraries :: Python Modules
